{
  "chain": {
    "block_number": 252764892,
    "collateral_ratio": 2.093965,
    "eth_price_usd": 2061.74978052,
    "liquidation_engine_paused": false,
    "oracle_stale": false,
    "total_collateral_eth": 8.125,
    "total_debt_nxusd": 8000.0,
    "vault_paused": false
  },
  "inputs": {
    "HAIRCUT_FLOOR_OK": true,
    "HAIRCUT_SCHEDULE_HASH_OK": true,
    "LCR": 2.093965,
    "LCR_1D": 2.093965,
    "LCR_30D": 2.093965,
    "LCR_7D": 2.093965,
    "LIABILITIES": 8000.0,
    "MATURITY_MISMATCH": 0.0,
    "MAX_ASSET_SHARE": 1.0,
    "NAV": 16751.716967,
    "PEG_RISK": false,
    "REFLEXIVITY_RISK": false,
    "RUNWAY_DAYS": 8.75,
    "RWA": 8000.0,
    "STRESS_BUFFER": 0.059396
  },
  "observed": {
    "checks": [
      {
        "msg": "NAV=16751.716967 LIAB=8000.0",
        "name": "I1_solvency_NAV_ge_LIAB",
        "ok": true
      },
      {
        "msg": "CCR=2.093964620875 MIN=1.05",
        "name": "I2_CCR_ge_CCR_MIN",
        "ok": true
      },
      {
        "msg": "LCR=2.093965 MIN=1.0",
        "name": "I3_LCR_ge_LCR_MIN",
        "ok": true
      },
      {
        "msg": "max=1.0 lim=0.35",
        "name": "I4_concentration",
        "ok": false
      },
      {
        "msg": "LEV=0.47756298746925935 lim=0.95",
        "name": "I5_leverage",
        "ok": true
      },
      {
        "msg": "haircut_floor_ok required",
        "name": "I6_haircut_floor",
        "ok": true
      },
      {
        "msg": "LCR_1D=2.093965 min=1.1",
        "name": "I10_LCR_1D",
        "ok": true
      },
      {
        "msg": "LCR_7D=2.093965 min=1.05",
        "name": "I10_LCR_7D",
        "ok": true
      },
      {
        "msg": "LCR_30D=2.093965 min=1.0",
        "name": "I10_LCR_30D",
        "ok": true
      },
      {
        "msg": "runway=8.75 min=30.0",
        "name": "I11_runway_days",
        "ok": false
      },
      {
        "msg": "mm=0.0 max=0.15",
        "name": "I12_maturity_mismatch",
        "ok": true
      },
      {
        "msg": "haircut_schedule_hash_ok required",
        "name": "I13_haircut_schedule_hash",
        "ok": true
      },
      {
        "msg": "CAR=1.093964620875 warn=0.02",
        "name": "S1_CAR_ge_warn",
        "ok": true
      },
      {
        "msg": "buf=0.059396 min=0.03",
        "name": "S2_stress_buffer",
        "ok": true
      },
      {
        "msg": "PEG_RISK=False",
        "name": "S3_peg_risk_flag",
        "ok": true
      },
      {
        "msg": "REFLEXIVITY_RISK=False",
        "name": "S4_reflexivity_flag",
        "ok": true
      }
    ],
    "decision": "FAIL",
    "mint_throttle": 0.0,
    "mode": "RECOVERY"
  },
  "pass": false,
  "policy_params": {
    "CAR_WARN": 0.02,
    "CCR_MIN": 1.05,
    "LCR_MIN": 1.0,
    "LCR_MIN_1D": 1.1,
    "LCR_MIN_30D": 1.0,
    "LCR_MIN_7D": 1.05,
    "MAX_CONCENTRATION": 0.35,
    "MAX_LEVERAGE": 0.95,
    "MAX_MATURITY_MISMATCH": 0.15,
    "RUNWAY_MIN_DAYS": 30.0,
    "STRESS_BUFFER_MIN": 0.03
  },
  "receipt_hash": "4b292aba0f207195397888609a71ac1288d3c130714829f0cb57c3cc12d6c8f7",
  "scenario_id": "SOV_003_LIVE_CHAIN_20260323T060942Z",
  "source": "LIVE_CHAIN",
  "suite_id": "SOV_003_CAPITAL_ADEQUACY_LAW_V1",
  "system_fingerprint": {
    "cwd": "/home/runner/work/nexus-120-engine/nexus-120-engine",
    "fingerprint_hash": "614ff85085b891e72180f9a51f1f274a199c6e888a8f11866bb5f76564688464",
    "git_head": "0eebc5e4fe1f7f99d13eedc63df2c0a7b2448291",
    "platform": "Linux-6.14.0-1017-azure-x86_64-with-glibc2.39",
    "python": "3.12.13"
  },
  "timestamp_utc": "2026-03-23T06:09:42Z"
}
